odoo8_addon_l10n_es_account_banking_sepa_fsdd-8.0.1.0.0.99.dev8-py3.6-nspkg.pth
odoo_addons/l10n_es_account_banking_sepa_fsdd/README.rst
odoo_addons/l10n_es_account_banking_sepa_fsdd/__init__.py
odoo_addons/l10n_es_account_banking_sepa_fsdd/__openerp__.py
odoo_addons/l10n_es_account_banking_sepa_fsdd/i18n/ca.po
odoo_addons/l10n_es_account_banking_sepa_fsdd/i18n/es.po
odoo_addons/l10n_es_account_banking_sepa_fsdd/i18n/fr.po
odoo_addons/l10n_es_account_banking_sepa_fsdd/i18n/l10n_es_account_banking_sepa_fsdd.pot
odoo_addons/l10n_es_account_banking_sepa_fsdd/i18n/nl.po
odoo_addons/l10n_es_account_banking_sepa_fsdd/i18n/pt_BR.po
odoo_addons/l10n_es_account_banking_sepa_fsdd/i18n/sl.po
odoo_addons/l10n_es_account_banking_sepa_fsdd/models/__init__.py
odoo_addons/l10n_es_account_banking_sepa_fsdd/models/payment_mode.py
odoo_addons/l10n_es_account_banking_sepa_fsdd/static/description/icon.png
odoo_addons/l10n_es_account_banking_sepa_fsdd/views/payment_mode_view.xml
odoo_addons/l10n_es_account_banking_sepa_fsdd/wizard/__init__.py
odoo_addons/l10n_es_account_banking_sepa_fsdd/wizard/banking_export_sdd_wzd.py
odoo8_addon_l10n_es_account_banking_sepa_fsdd-8.0.1.0.0.99.dev8.dist-info/METADATA
odoo8_addon_l10n_es_account_banking_sepa_fsdd-8.0.1.0.0.99.dev8.dist-info/WHEEL
odoo8_addon_l10n_es_account_banking_sepa_fsdd-8.0.1.0.0.99.dev8.dist-info/namespace_packages.txt
odoo8_addon_l10n_es_account_banking_sepa_fsdd-8.0.1.0.0.99.dev8.dist-info/top_level.txt
odoo8_addon_l10n_es_account_banking_sepa_fsdd-8.0.1.0.0.99.dev8.dist-info/RECORD
