Metadata-Version: 2.1
Name: odoo8-addon-l10n-es-account-banking-sepa-fsdd
Version: 8.0.1.0.0.99.dev8
Summary: Account Banking Sepa - FSDD (Anticipos de crédito)
Home-page: http://www.comunitea.com
Author: Comunitea,Odoo Community Association (OCA)
Author-email: support@odoo-community.org
License: UNKNOWN
Platform: UNKNOWN
Classifier: Programming Language :: Python
Classifier: Framework :: Odoo
Requires-Python: ~=2.7
Requires-Dist: odoo8-addon-account-banking-sepa-direct-debit
Requires-Dist: odoo (<9.0a,>=8.0a)
